un1qnx/__init__.py
un1qnx/base.py
un1qnx/product.py
un1qnx/tag.py
un1qnx_api-0.2.0.dist-info/METADATA
un1qnx_api-0.2.0.dist-info/WHEEL
un1qnx_api-0.2.0.dist-info/top_level.txt
un1qnx_api-0.2.0.dist-info/RECORD
